openai_is_even/__init__.py
openai_is_even/ai.py
openai_is_even-1.0.1.dist-info/WHEEL
openai_is_even-1.0.1.dist-info/METADATA
openai_is_even-1.0.1.dist-info/RECORD
