Metadata-Version: 2.3
Name: openai-is-even
Version: 1.0.1
Summary: A Python package that uses OpenAI to check if numbers are even
Keywords: openai,even,odd,numbers,ai
Author: d-costa
Requires-Dist: openai>=1.0.0
Requires-Python: >=3.10
Project-URL: Homepage, https://github.com/d-costa/openai_is_even
Project-URL: Issues, https://github.com/d-costa/openai_is_even/issues
Project-URL: Repository, https://github.com/d-costa/openai_is_even
